sphinx_imgur/__init__.py
sphinx_imgur/imgur.py
sphinx_imgur/nodes.py
sphinx_imgur/utils.py
sphinx_imgur-3.0.0.dist-info/COPYING
sphinx_imgur-3.0.0.dist-info/LICENSE
sphinx_imgur-3.0.0.dist-info/WHEEL
sphinx_imgur-3.0.0.dist-info/METADATA
sphinx_imgur-3.0.0.dist-info/RECORD
