Metadata-Version: 2.1
Name: sphinx-imgur
Version: 3.0.0
Summary: Embed Imgur images and albums in Sphinx documents/pages.
License: BSD-2-Clause
Author: Robpol86
Author-email: robpol86@gmail.com
Requires-Python: >=3.6.2,<4.0.0
Classifier: Development Status :: 5 - Production/Stable
Classifier: Environment :: MacOS X
Classifier: Environment :: Plugins
Classifier: Environment :: Win32 (MS Windows)
Classifier: Framework :: Sphinx :: Extension
Classifier: Intended Audience :: Developers
Classifier: License :: OSI Approved :: BSD License
Classifier: Operating System :: MacOS :: MacOS X
Classifier: Operating System :: Microsoft :: Windows
Classifier: Operating System :: POSIX
Classifier: Operating System :: POSIX :: Linux
Classifier: Programming Language :: Python :: 3
Classifier: Programming Language :: Python :: 3 :: Only
Classifier: Programming Language :: Python :: 3.10
Classifier: Programming Language :: Python :: 3.6
Classifier: Programming Language :: Python :: 3.7
Classifier: Programming Language :: Python :: 3.8
Classifier: Programming Language :: Python :: 3.9
Classifier: Topic :: Documentation :: Sphinx
Classifier: Topic :: Software Development :: Documentation
Provides-Extra: docs
Requires-Dist: sphinx
Requires-Dist: sphinx-copybutton; extra == "docs"
Requires-Dist: sphinx-notfound-page; extra == "docs"
Requires-Dist: sphinx-panels; extra == "docs"
Requires-Dist: sphinx-rtd-theme; extra == "docs"
Requires-Dist: sphinxext-opengraph; extra == "docs"
Requires-Dist: toml; extra == "docs"
Project-URL: documentation, https://sphinx-imgur.readthedocs.io
Project-URL: repository, https://github.com/Robpol86/sphinx-imgur
